Source/apb_reg.v
`timescale 1ns/1ps

module apb_regs #(
    parameter DW = 32,
    parameter AW = 5
)(
    input                  pclk,
    input                  presetn,
    
    input      [AW-1:0]    paddr,
    input                  psel,
    input                  penable,
    input                  pwrite,
    output                 pready,
    input      [DW-1:0]    pwdata,
    output reg    [DW-1:0]    prdata,
    output                 pslverr



    //user ports
);

    reg [DW-1:0] slv_reg0;
    reg [DW-1:0] slv_reg1;
    reg [DW-1:0] slv_reg2;
    reg [DW-1:0] slv_reg3;

    wire apb_write = psel & penable & pwrite;
    wire apb_read  = psel & ~pwrite;

    assign pready = 1'b1; 
    assign pslverr = 1'b0;

    always @(posedge pclk or negedge presetn) begin
        if (!presetn) begin
            slv_reg0 <= 32'b0;
            slv_reg1 <= 32'b0;
            slv_reg2 <= 32'b0;
            slv_reg3 <= 32'b0;
        end else if (apb_write) begin
            case (paddr)
                5'h00: slv_reg0 <= pwdata;
                5'h04: slv_reg1 <= pwdata;
                5'h08: slv_reg2 <= pwdata;
                5'h0C: slv_reg3 <= pwdata;
                default: begin
						  slv_reg0 <= slv_reg0;
	                      slv_reg1 <= slv_reg1;
	                      slv_reg2 <= slv_reg2;
	                      slv_reg3 <= slv_reg3;
				end
            endcase
        end
    end

    // Register read logic
always @(posedge pclk or negedge presetn) begin
    if (!presetn) begin
        prdata <= {DW{1'b0}};
    end else if (apb_read) begin
        case (paddr)
            5'h00: prdata <= slv_reg0;
            5'h04: prdata <= slv_reg1;
            5'h08: prdata <= slv_reg2;
            5'h0C: prdata <= slv_reg3;
            default: prdata <= {DW{1'b0}};
        endcase
    end
end

endmodule

Source/tb_apb_reg.v
`include "apb_reg.v"
`timescale 1ns/1ps

module apb_regs_tb;

  parameter DW = 32;
  parameter AW = 5;

  reg                  pclk;
  reg                  presetn;
  reg  [AW-1:0]        paddr;
  reg                  psel;
  reg                  penable;
  reg                  pwrite;
  reg  [DW-1:0]        pwdata;
  wire [DW-1:0]        prdata;
  wire                 pready;
  wire                 pslverr;

  apb_regs #(.DW(DW), .AW(AW)) dut (
    .pclk     (pclk),
    .presetn  (presetn),
    .paddr    (paddr),
    .psel     (psel),
    .penable  (penable),
    .pwrite   (pwrite),
    .pready   (pready),
    .pwdata   (pwdata),
    .prdata   (prdata),
    .pslverr  (pslverr)
  );

  // 클럭 생성 (50MHz)
  initial pclk = 0;
  always #10 pclk = ~pclk;

  reg [DW-1:0] rdata;

  // APB 쓰기 task
  task apb_write;
    input [AW-1:0] addr;
    input [DW-1:0] data;
    begin
      @(posedge pclk);
      paddr   = addr;
      pwdata  = data;
      pwrite  = 1;
      psel    = 1;
      penable = 0;
      @(posedge pclk);
      penable = 1;
      @(posedge pclk);
      wait (pready);
      @(posedge pclk);
      psel    = 0;
      penable = 0;
      pwrite  = 0;
    end
  endtask

  // APB 읽기 task
  task apb_read;
    input [AW-1:0] addr;
    begin
      @(posedge pclk);
      paddr   = addr;
      pwrite  = 0;
      psel    = 1;
      penable = 0;
      @(posedge pclk);
      penable = 1;
      @(posedge pclk);
      wait (pready);
      @(posedge pclk);
      rdata = prdata;
      psel  = 0;
      penable = 0;
    end
  endtask

  // 테스트 시나리오
  initial begin
    // 초기화
    paddr   = 0;
    psel    = 0;
    penable = 0;
    pwrite  = 0;
    pwdata  = 0;
    presetn = 0;

    // 파형 출력
    $dumpfile("apb_regs_tb.vcd");
    $dumpvars(0, apb_regs_tb);

    // 리셋
    repeat (2) @(posedge pclk);
    presetn = 1;

    $display("==== APB 테스트 시작 ====");

    // 쓰기
    apb_write(5'h00, 32'hAAAA_1111);
    apb_write(5'h04, 32'hBBBB_2222);
    apb_write(5'h08, 32'hCCCC_3333);
    apb_write(5'h0C, 32'hDDDD_4444);

    #20;

    // 읽기 및 출력
    apb_read(5'h00); $display("Read @0x00 = %h", rdata);
    apb_read(5'h04); $display("Read @0x04 = %h", rdata);
    apb_read(5'h08); $display("Read @0x08 = %h", rdata);
    apb_read(5'h0C); $display("Read @0x0C = %h", rdata);

    #20;
    $display("==== APB 테스트 완료 ====");
    $finish;
  end

endmodule

Source/apb_regs_tb.vcd
$date
	Tue Apr 15 22:25:54 2025
$end
$version
	Icarus Verilog
$end
$timescale
	1ps
$end
$scope module apb_regs_tb $end
$var wire 1 ! pready $end
$var wire 1 " pslverr $end
$var wire 32 # prdata [31:0] $end
$var parameter 32 $ AW $end
$var parameter 32 % DW $end
$var reg 5 & paddr [4:0] $end
$var reg 1 ' pclk $end
$var reg 1 ( penable $end
$var reg 1 ) presetn $end
$var reg 1 * psel $end
$var reg 32 + pwdata [31:0] $end
$var reg 1 , pwrite $end
$var reg 32 - rdata [31:0] $end
$scope module dut $end
$var wire 1 . apb_read $end
$var wire 1 / apb_write $end
$var wire 5 0 paddr [4:0] $end
$var wire 1 ' pclk $end
$var wire 1 ( penable $end
$var wire 1 ! pready $end
$var wire 1 ) presetn $end
$var wire 1 * psel $end
$var wire 1 " pslverr $end
$var wire 32 1 pwdata [31:0] $end
$var wire 1 , pwrite $end
$var parameter 32 2 AW $end
$var parameter 32 3 DW $end
$var reg 32 4 prdata [31:0] $end
$var reg 32 5 slv_reg0 [31:0] $end
$var reg 32 6 slv_reg1 [31:0] $end
$var reg 32 7 slv_reg2 [31:0] $end
$var reg 32 8 slv_reg3 [31:0] $end
$upscope $end
$scope task apb_read $end
$var reg 5 9 addr [4:0] $end
$upscope $end
$scope task apb_write $end
$var reg 5 : addr [4:0] $end
$var reg 32 ; data [31:0] $end
$upscope $end
$upscope $end
$enddefinitions $end
$comment Show the parameter values. $end
$dumpall
b100000 3
b101 2
b100000 %
b101 $
$end
#0
$dumpvars
bx ;
bx :
bx 9
b0 8
b0 7
b0 6
b0 5
b0 4
b0 1
b0 0
0/
0.
bx -
0,
b0 +
0*
0)
0(
0'
b0 &
b0 #
0"
1!
$end
#10000
1'
#20000
0'
#30000
b10101010101010100001000100010001 ;
b0 :
1)
1'
#40000
0'
#50000
1*
1,
b10101010101010100001000100010001 +
b10101010101010100001000100010001 1
1'
#60000
0'
#70000
1/
1(
1'
#80000
0'
#90000
b10101010101010100001000100010001 5
1'
#100000
0'
#110000
0/
b10111011101110110010001000100010 ;
b100 :
0,
0(
0*
1'
#120000
0'
#130000
1*
1,
b10111011101110110010001000100010 +
b10111011101110110010001000100010 1
b100 &
b100 0
1'
#140000
0'
#150000
1/
1(
1'
#160000
0'
#170000
b10111011101110110010001000100010 6
1'
#180000
0'
#190000
0/
b11001100110011000011001100110011 ;
b1000 :
0,
0(
0*
1'
#200000
0'
#210000
1*
1,
b11001100110011000011001100110011 +
b11001100110011000011001100110011 1
b1000 &
b1000 0
1'
#220000
0'
#230000
1/
1(
1'
#240000
0'
#250000
b11001100110011000011001100110011 7
1'
#260000
0'
#270000
0/
b11011101110111010100010001000100 ;
b1100 :
0,
0(
0*
1'
#280000
0'
#290000
1*
1,
b11011101110111010100010001000100 +
b11011101110111010100010001000100 1
b1100 &
b1100 0
1'
#300000
0'
#310000
1/
1(
1'
#320000
0'
#330000
b11011101110111010100010001000100 8
1'
#340000
0'
#350000
0/
0,
0(
0*
1'
#360000
0'
#370000
1.
1*
b0 &
b0 0
1'
b0 9
#380000
0'
#390000
b10101010101010100001000100010001 #
b10101010101010100001000100010001 4
1(
1'
#400000
0'
#410000
1'
#420000
0'
#430000
0.
b100 9
0(
0*
b10101010101010100001000100010001 -
1'
#440000
0'
#450000
1.
1*
b100 &
b100 0
1'
#460000
0'
#470000
b10111011101110110010001000100010 #
b10111011101110110010001000100010 4
1(
1'
#480000
0'
#490000
1'
#500000
0'
#510000
0.
b1000 9
0(
0*
b10111011101110110010001000100010 -
1'
#520000
0'
#530000
1.
1*
b1000 &
b1000 0
1'
#540000
0'
#550000
b11001100110011000011001100110011 #
b11001100110011000011001100110011 4
1(
1'
#560000
0'
#570000
1'
#580000
0'
#590000
0.
b1100 9
0(
0*
b11001100110011000011001100110011 -
1'
#600000
0'
#610000
1.
1*
b1100 &
b1100 0
1'
#620000
0'
#630000
b11011101110111010100010001000100 #
b11011101110111010100010001000100 4
1(
1'
#640000
0'
#650000
1'
#660000
0'
#670000
0.
0(
0*
b11011101110111010100010001000100 -
1'
